datasetloader/__init__.py
datasetloader/base.py
datasetloader/fashion_mnist.py
datasetloader/mnist.py
datasetloader/newsgroups.py
therrshan_datasetloader-0.1.1.dist-info/METADATA
therrshan_datasetloader-0.1.1.dist-info/WHEEL
therrshan_datasetloader-0.1.1.dist-info/top_level.txt
therrshan_datasetloader-0.1.1.dist-info/RECORD
