Metadata-Version: 2.4
Name: therrshan-datasetloader
Version: 0.1.1
Summary: Local loader for MNIST, Fashion MNIST, and 20 Newsgroups datasets
Author: Darshan Rajopadhye
License: MIT
Requires-Dist: numpy
Requires-Dist: pandas
Dynamic: author
Dynamic: license
Dynamic: requires-dist
Dynamic: summary
